MANIFEST.in
README.md
setup.py
longtraceback/ChangedVariables.py
longtraceback/CodeNaming.py
longtraceback/DescribeSequence.py
longtraceback/DisplayHook.py
longtraceback/ExceptHook.py
longtraceback/Extensions.py
longtraceback/Options.py
longtraceback/ReduceFilename.py
longtraceback/ReprPatching.py
longtraceback/Styling.py
longtraceback/SysUtils.py
longtraceback/ValueFormat.py
longtraceback/Variables.py
longtraceback/__init__.py
longtraceback/shell.py
longtraceback.egg-info/PKG-INFO
longtraceback.egg-info/SOURCES.txt
longtraceback.egg-info/dependency_links.txt
longtraceback.egg-info/top_level.txt
styledstrings/StyledString.py
styledstrings/__init__.py