Metadata-Version: 2.1
Name: longtraceback
Version: 1.0.356
Summary: More information about variables and context within traceback
Home-page: https://gitlab.gerph.org/gerph/longtraceback
Author: Charles Ferguson
Author-email: gerph@gerph.org
License: MIT
Keywords: traceback
Platform: UNKNOWN
Classifier: Development Status :: 4 - Beta
Classifier: Intended Audience :: Developers
Classifier: License :: OSI Approved :: MIT License
Classifier: Programming Language :: Python :: 2.7
Classifier: Programming Language :: Python :: 3
Classifier: Operating System :: OS Independent
Requires-Python: >=2.7
